tc2100/__init__.py
tc2100/__main__.py
tc2100/discover.py
tc2100/observation.py
tc2100/protocol.py
tc2100/version.py
tc2100-0.1.5.dist-info/entry_points.txt
tc2100-0.1.5.dist-info/LICENSE
tc2100-0.1.5.dist-info/WHEEL
tc2100-0.1.5.dist-info/METADATA
tc2100-0.1.5.dist-info/RECORD
