Metadata-Version: 2.1
Name: tc2100
Version: 0.1.5
Summary: Receive data from a compatible USB digital thermometer
License: MIT
Author: Colin S.
Author-email: 3526918+cbs228@users.noreply.github.com
Requires-Python: >=3.8,<4.0
Classifier: Development Status :: 4 - Beta
Classifier: Environment :: Console
Classifier: Framework :: Twisted
Classifier: Intended Audience :: Developers
Classifier: Intended Audience :: Science/Research
Classifier: License :: OSI Approved :: MIT License
Classifier: Operating System :: OS Independent
Classifier: Programming Language :: Python :: 3
Classifier: Programming Language :: Python :: 3.10
Classifier: Programming Language :: Python :: 3.8
Classifier: Programming Language :: Python :: 3.9
Classifier: Topic :: Software Development :: Libraries :: Python Modules
Classifier: Topic :: System :: Hardware :: Hardware Drivers
Provides-Extra: docs
Requires-Dist: m2r2 (>=0.3.2,<0.4.0); extra == "docs"
Requires-Dist: pyserial (>=3.4,<4.0)
Requires-Dist: sphinx (>=1.6.7,<1.7.0); extra == "docs"
Requires-Dist: sphinx_rtd_theme (>=1.0.0,<1.1.0); extra == "docs"
Requires-Dist: twisted (>=22.1,<23.0)
